CHANGELOG.md
LICENSE
mnemo/__init__.py
mnemo/autocomplete/.mnemo-complete.bash
mnemo/autocomplete/.mnemo-complete.fish
mnemo/autocomplete/.mnemo-complete.zsh
mnemo/bottled/__init__.py
mnemo/bottled/apps.py
mnemo/bottled/css/bootstrap.min.css
mnemo/bottled/css/bootstrap.min.css.map
mnemo/bottled/css/main.css
mnemo/bottled/db/.gitignore
mnemo/bottled/js/bootstrap.bundle.min.js
mnemo/bottled/js/bootstrap.bundle.min.js.map
mnemo/bottled/js/jquery-3.6.0.min.js
mnemo/bottled/js/main.js
mnemo/bottled/js/page.assistant-scene.js
mnemo/bottled/js/page.first_setup.js
mnemo/bottled/js/page.login.js
mnemo/bottled/js/page.password-edit.js
mnemo/bottled/js/page.profile.js
mnemo/bottled/js/three.module.js
mnemo/bottled/routes.py
mnemo/bottled/templates/base.html
mnemo/bottled/templates/buttons/home_button.html
mnemo/bottled/templates/buttons/journal_button.html
mnemo/bottled/templates/buttons/logout_button.html
mnemo/bottled/templates/buttons/notes_button.html
mnemo/bottled/templates/buttons/profile_button.html
mnemo/bottled/templates/forms/first_setup.html
mnemo/bottled/templates/forms/login.html
mnemo/bottled/templates/forms/password-edit.html
mnemo/bottled/templates/includes/assistant-scene.html
mnemo/bottled/templates/includes/main-menu.html
mnemo/bottled/templates/pages/home.html
mnemo/bottled/templates/pages/journal.html
mnemo/bottled/templates/pages/notes.html
mnemo/bottled/templates/pages/profile.html
mnemo/bottled/templates/responses/first_setup_response.html
mnemo/bottled/templates/responses/login_response.html
mnemo/bottled/templates/responses/logout_response.html
mnemo/bottled/templates/responses/profile_edit_field_response.html
mnemo/const.py
mnemo/scripts/__init__.py
mnemo/scripts/assistant.py
mnemo/scripts/autocomplete.py
mnemo/session.py
mnemo/tests/test_main.py
mnemo-0.0.2.dist-info/entry_points.txt
mnemo-0.0.2.dist-info/LICENSE
mnemo-0.0.2.dist-info/WHEEL
mnemo-0.0.2.dist-info/METADATA
mnemo-0.0.2.dist-info/RECORD
